LICENSE
MANIFEST.in
README.rst
setup.cfg
setup.py
pykc/__init__.py
pykc/core.py
pykc/exceptions.py
pykc/http.py
pykc/parser.py
pykc.egg-info/PKG-INFO
pykc.egg-info/SOURCES.txt
pykc.egg-info/dependency_links.txt
pykc.egg-info/not-zip-safe
pykc.egg-info/requires.txt
pykc.egg-info/top_level.txt
pykc/objects/__init__.py
pykc/objects/mod.py
pykc/objects/post.py
pykc/objects/thread.py