Metadata-Version: 1.1
Name: pykc
Version: 1.0
Summary: Feed your snake with your favourite imageboard.
Home-page: http://github.com/buckket/pykc
Author: buckket
Author-email: UNKNOWN
License: WTFPL
Keywords: imageboard,kc,parser
Platform: any
Classifier: Development Status :: 4 - Beta
Classifier: License :: Public Domain
Classifier: Operating System :: OS Independent
Classifier: Intended Audience :: Developers
Classifier: Programming Language :: Python
